README.md
setup.py
ganesh/__init__.py
ganesh/app.py
ganesh.egg-info/PKG-INFO
ganesh.egg-info/SOURCES.txt
ganesh.egg-info/dependency_links.txt
ganesh.egg-info/requires.txt
ganesh.egg-info/top_level.txt